SpatialEx/SpatialEx_pyG.py
SpatialEx/__init__.py
SpatialEx/model.py
SpatialEx/preprocess.py
SpatialEx/utils.py
spatialex-0.1.6.dist-info/LICENSE.md
spatialex-0.1.6.dist-info/METADATA
spatialex-0.1.6.dist-info/WHEEL
spatialex-0.1.6.dist-info/top_level.txt
spatialex-0.1.6.dist-info/RECORD
