Metadata-Version: 2.1
Name: SpatialEx
Version: 0.1.6
Summary: computational frameworks that leverage histology as a universal anchor to integrate spatial molecular data across tissue sections
Home-page: https://github.com/KEAML-JLU/SpatialEx
Author: Yonghao Liu and Chuyao Wang
Author-email: yonghao20@mails.jlu.edu.cn
License: MIT
License-File: LICENSE.md
Requires-Dist: requests
